CS270Boi/__init__.py
CS270Boi/discussion270.py
CS270Boi-1.3.3.dist-info/LICENSE
CS270Boi-1.3.3.dist-info/METADATA
CS270Boi-1.3.3.dist-info/WHEEL
CS270Boi-1.3.3.dist-info/top_level.txt
CS270Boi-1.3.3.dist-info/RECORD
