Metadata-Version: 2.1
Name: CS270Boi
Version: 1.3.3
Summary: An awesome package for discussions.
Home-page: http://pypi.python.org/pypi/CS270Boi/
Author: Jake Cahoon
Author-email: jacobbcahoon@gmail.com
License: LICENSE.txt
License-File: LICENSE
Requires-Dist: ipywidgets
Requires-Dist: IPython
